cloudRunStayAwake/LICENSE
cloudRunStayAwake/README.md
cloudRunStayAwake/__init__.py
cloudRunStayAwake/cloudRunStayAwake.py
cloudRunStayAwake/test.py
cloudRunStayAwake-1.0.5.dist-info/LICENSE
cloudRunStayAwake-1.0.5.dist-info/METADATA
cloudRunStayAwake-1.0.5.dist-info/WHEEL
cloudRunStayAwake-1.0.5.dist-info/top_level.txt
cloudRunStayAwake-1.0.5.dist-info/RECORD
