Metadata-Version: 2.1
Name: cloudRunStayAwake
Version: 1.0.5
Summary: Reduce Cloud Run cold start with targetted self call
Home-page: https://github.com/Resousse/cloudrun-stay-awake
Author: Resousse
Author-email: resousegit@gmail.com
License: Apache 2.0
Platform: UNKNOWN
License-File: LICENSE
Requires-Dist: requests
